nonebot_plugin_qqshell/__init__.py
nonebot_plugin_qqshell/config.py
nonebot_plugin_qqshell/handler.py
nonebot_plugin_qqshell/services.py
nonebot_plugin_qqshell/static/images/rikka1.png
nonebot_plugin_qqshell/template_env.py
nonebot_plugin_qqshell/templates/shell_panel.html
nonebot_plugin_qqshell/templates/xterm.html
nonebot_plugin_qqshell/utils/__init__.py
nonebot_plugin_qqshell/utils/shell.py
nonebot_plugin_qqshell-0.1.0.dist-info/METADATA
nonebot_plugin_qqshell-0.1.0.dist-info/WHEEL
nonebot_plugin_qqshell-0.1.0.dist-info/RECORD
