Metadata-Version: 2.1
Name: nonebot-plugin-qqshell
Version: 0.1.0
Summary: QQShell 是一个类 WebSSH、XShell 的运行在机器人的 SSH Shell，在 QQ 中自由运行你的命令吧
License: GPLv3
Author: yejue
Author-email: 1145331931@qq.com
Requires-Python: >=3.10,<4.0
Classifier: License :: Other/Proprietary License
Classifier: Programming Language :: Python :: 3
Classifier: Programming Language :: Python :: 3.10
Classifier: Programming Language :: Python :: 3.11
Classifier: Programming Language :: Python :: 3.12
Requires-Dist: nonebot-adapter-onebot (>=2.4.3,<3.0.0)
Requires-Dist: nonebot2 (>=2.2,<3.0)
Requires-Dist: nonebot_plugin_htmlrender (>=0.3.1,<0.4.0)
Requires-Dist: paramiko (>=3.4,<4.0)
Project-URL: homepage, https://github.com/yejue/nonebot-plugin-qqshell.git
Project-URL: repository, https://github.com/yejue/nonebot-plugin-qqshell.git
